llm_monitor/__init__.py
llm_monitor/constants/__init__.py
llm_monitor/constants/routes.py
llm_monitor/handlers.py
llm_monitor/monitor.py
llm_monitor/schema/__init__.py
llm_monitor/schema/transaction.py
llm_monitor/utils/__init__.py
llm_monitor/utils/api_client.py
llm_monitor/utils/request.py
llm_monitor-0.19.1.dist-info/LICENSE
llm_monitor-0.19.1.dist-info/METADATA
llm_monitor-0.19.1.dist-info/WHEEL
llm_monitor-0.19.1.dist-info/RECORD
